TSC/__init__.py
TSC/Design/ConfimentBarsRules.py
TSC/Design/Definitions.py
TSC/Design/Error.py
TSC/Design/Frp.py
TSC/Design/GlobalParamCheck.py
TSC/Design/MaterialModels.py
TSC/Design/ResponseSpectra.py
TSC/Design/SeismicLoad.py
TSC/Design/__init__.py
TSC/MSCSI/AnalysisResult.py
TSC/MSCSI/Analyze.py
TSC/MSCSI/CaseStaticNonlinear.py
TSC/MSCSI/Combo.py
TSC/MSCSI/Connector.py
TSC/MSCSI/Database.py
TSC/MSCSI/Enums.py
TSC/MSCSI/ErrorHandler.py
TSC/MSCSI/File.py
TSC/MSCSI/Frame.py
TSC/MSCSI/FunctionRS.py
TSC/MSCSI/LoadCases.py
TSC/MSCSI/LoadPattern.py
TSC/MSCSI/MaterialProp.py
TSC/MSCSI/Model.py
TSC/MSCSI/PluginCallback.py
TSC/MSCSI/Story.py
TSC/MSCSI/__init__.py
TSC/Resource/__init__.py
TSC/Utility/Decorators.py
TSC/Utility/__init__.py
TSC2018_Design-1.1.5.dist-info/LICENSE
TSC2018_Design-1.1.5.dist-info/METADATA
TSC2018_Design-1.1.5.dist-info/WHEEL
TSC2018_Design-1.1.5.dist-info/top_level.txt
TSC2018_Design-1.1.5.dist-info/RECORD
