Metadata-Version: 2.1
Name: TSC2018_Design
Version: 1.1.5
Summary: TSC2018 design
Author-email: Muhammed Sural <muhammedsural@gmail.com>
Project-URL: Homepage, https://github.com/muhammedsural/TSC2018_Design
Project-URL: Bug Tracker, https://github.com/muhammedsural/TSC2018_Design/issues
Keywords: TSC2018,ETABS,SAP2000,DESIGN,TS500-2000
Classifier: Programming Language :: Python :: 3
Classifier: License :: OSI Approved :: MIT License
Classifier: Operating System :: OS Independent
Requires-Python: >=3.10
License-File: LICENSE
Requires-Dist: matplotlib
Requires-Dist: pandas
Requires-Dist: numpy
Requires-Dist: scipy
Requires-Dist: pytest
Requires-Dist: attrs >=23.0.0
Requires-Dist: comtypes
